doma/__init__.py
doma-0.0.1a1.dist-info/METADATA
doma-0.0.1a1.dist-info/WHEEL
doma-0.0.1a1.dist-info/top_level.txt
doma-0.0.1a1.dist-info/RECORD
