Metadata-Version: 2.4
Name: doma
Version: 0.0.1a1
Summary: A household management application.
Author-email: Sébastien Hocquet <seb@ipamo.net>
Classifier: Development Status :: 1 - Planning
Classifier: Environment :: Web Environment
Requires-Python: >=3.11
